LICENSE
MANIFEST.in
README.md
requirements.txt
setup.py
pyieoe/__init__.py
pyieoe/base.py
pyieoe/evaluator.py
pyieoe/utils.py
pyieoe/version.py
pyieoe.egg-info/PKG-INFO
pyieoe.egg-info/SOURCES.txt
pyieoe.egg-info/dependency_links.txt
pyieoe.egg-info/requires.txt
pyieoe.egg-info/top_level.txt