Metadata-Version: 2.1
Name: pyieoe
Version: 0.1.1
Summary: pyIEOE: a Python package to facilitate interpretable OPE evaluation
Home-page: https://github.com/sony/pyIEOE
License: MIT License
Keywords: off-policy evaluation
Platform: UNKNOWN
Classifier: Topic :: Scientific/Engineering :: Artificial Intelligence
Classifier: Intended Audience :: Science/Research
Classifier: Programming Language :: Python :: 3.7
Classifier: Programming Language :: Python :: 3.8
Classifier: Programming Language :: Python :: 3.9
